orbit_count.libs/libgomp-a34b3233.so.1.0.0
orbit_count-0.1.0.dist-info/WHEEL
orbit_count-0.1.0.dist-info/RECORD
orbit_count-0.1.0.dist-info/METADATA
orbit_count-0.1.0.dist-info/licenses/LICENSE.md
orbit_count-0.1.0.dist-info/licenses/LICENSE.wheel.md
orbit_count/_orca.cpython-39-x86_64-linux-gnu.so
orbit_count/__init__.py
