Metadata-Version: 2.1
Name: orbit-count
Version: 0.1.0
Summary: Python bindings for the ORbit Counting Algorithm
Author-Email: Markus Krimmel <krimmel@biochem.mpg.de>, Philip Hartout <hartout@biochem.mpg.de>
License: The source of this package is licensed under GPL v3. The wheels may bundle an external implementation of OpenMP as a dynamically linked library. We refer to LICENSE.wheel.md for further information.
Project-URL: Repository, https://github.com/BorgwardtLab/orbit-count
Requires-Python: >=3.7
Requires-Dist: numpy
Requires-Dist: networkx
Requires-Dist: pytest; extra == "dev"
Requires-Dist: pytest-xdist; extra == "dev"
Requires-Dist: memory_profiler; extra == "dev"
Requires-Dist: ruff; extra == "dev"
Requires-Dist: pre-commit; extra == "dev"
Provides-Extra: dev
